toggl/__init__.py
toggl/__main__.py
toggl/exceptions.py
toggl/toggl.py
toggl/api/__init__.py
toggl/api/base.py
toggl/api/fields.py
toggl/api/models.py
toggl/assets/icon.png
toggl/cli/__init__.py
toggl/cli/commands.py
toggl/cli/helpers.py
toggl/cli/themes.py
toggl/cli/types.py
toggl/utils/__init__.py
toggl/utils/bootstrap.py
toggl/utils/config.py
toggl/utils/metas.py
toggl/utils/migrations.py
toggl/utils/others.py
togglcli-4.0.0.dist-info/licenses/LICENSE
togglcli-4.0.0.dist-info/METADATA
togglcli-4.0.0.dist-info/WHEEL
togglcli-4.0.0.dist-info/entry_points.txt
togglcli-4.0.0.dist-info/pbr.json
togglcli-4.0.0.dist-info/top_level.txt
togglcli-4.0.0.dist-info/RECORD
