Metadata-Version: 2.4
Name: togglCli
Version: 4.0.0
Summary: Command line tool and set of Python wrapper classes for interacting with toggl's API
Home-page: https://toggl.uhlir.dev
Author: D. Robert Adams & Adam Uhlir
Author-email: adam@uhlir.dev
License: MIT
Project-URL: Source, https://github.com/auhau/toggl-cli
Project-URL: Documentation, https://toggl.uhlir.devg
Classifier: License :: OSI Approved :: MIT License
Classifier: Programming Language :: Python
Classifier: Programming Language :: Python :: 3
Classifier: Programming Language :: Python :: 3.9
Classifier: Programming Language :: Python :: 3.10
Classifier: Programming Language :: Python :: 3.11
Classifier: Programming Language :: Python :: 3.12
Classifier: Programming Language :: Python :: 3.13
Classifier: Programming Language :: Python :: Implementation :: CPython
Classifier: Development Status :: 5 - Production/Stable
Classifier: Topic :: Office/Business :: Scheduling
Classifier: Intended Audience :: End Users/Desktop
Classifier: Intended Audience :: Developers
Requires-Python: >=3.9.0
License-File: LICENSE
Requires-Dist: setuptools==80.7.1
Requires-Dist: pendulum==3.1.0
Requires-Dist: requests>=2.23.0
Requires-Dist: click==8.1.7
Requires-Dist: inquirer==3.2.4
Requires-Dist: prettytable==3.6.0
Requires-Dist: validate_email==1.3
Requires-Dist: click-completion==0.5.2
Requires-Dist: pbr==6.1.1
Requires-Dist: notify-py==0.3.42
Dynamic: author
Dynamic: author-email
Dynamic: classifier
Dynamic: description
Dynamic: description-content-type
Dynamic: home-page
Dynamic: license
Dynamic: license-file
Dynamic: project-url
Dynamic: requires-dist
Dynamic: requires-python
Dynamic: summary
